principal_package/__init__.py
principal_package/__pycache__/__init__.cpython-313.pyc
principal_package/__pycache__/funtions.cpython-313.pyc
principal_package-0.2.1.dist-info/METADATA
principal_package-0.2.1.dist-info/WHEEL
principal_package-0.2.1.dist-info/top_level.txt
principal_package-0.2.1.dist-info/RECORD
