Metadata-Version: 2.4
Name: principal_package
Version: 0.2.1
Summary: Librería proyecto brasil
Author: Sebastian Castro
License: MIT
Classifier: Programming Language :: Python :: 3
Classifier: Programming Language :: Python :: 3 :: Only
Classifier: Programming Language :: Python :: 3.9
Classifier: Programming Language :: Python :: 3.10
Classifier: Programming Language :: Python :: 3.11
Classifier: Programming Language :: Python :: 3.12
Classifier: Programming Language :: Python :: 3.13
Classifier: License :: OSI Approved :: MIT License
Classifier: Operating System :: OS Independent
Classifier: Topic :: Scientific/Engineering :: Information Analysis
Classifier: Intended Audience :: Science/Research
Requires-Python: >=3.9
Provides-Extra: full
Requires-Dist: scikit-learn>=1.4; extra == "full"
Requires-Dist: umap-learn>=0.5.5; extra == "full"
Requires-Dist: hdbscan>=0.8.38; extra == "full"
Requires-Dist: jinja2>=3.1; extra == "full"
Requires-Dist: openpyxl>=3.1; extra == "full"
Requires-Dist: tqdm>=4.65; extra == "full"
Requires-Dist: joblib>=1.3; extra == "full"
Requires-Dist: matplotlib>=3.8; extra == "full"
Requires-Dist: numpy>=1.23; extra == "full"
Requires-Dist: pandas>=1.5; extra == "full"
Requires-Dist: seaborn>=0.12; extra == "full"
Requires-Dist: plotly>=5.15; extra == "full"
Dynamic: author
Dynamic: classifier
Dynamic: description
Dynamic: description-content-type
Dynamic: license
Dynamic: provides-extra
Dynamic: requires-python
Dynamic: summary
